justblast/__init__.py
justblast/__version__.py
justblast/justblast_main.py
justblast/utils.py
justblast-2020.0.4.data/scripts/justblast
justblast-2020.0.4.dist-info/METADATA
justblast-2020.0.4.dist-info/WHEEL
justblast-2020.0.4.dist-info/dependency_links.txt
justblast-2020.0.4.dist-info/top_level.txt
justblast-2020.0.4.dist-info/RECORD
