Metadata-Version: 2.1
Name: justblast
Version: 2020.0.4
Summary: Simple program to more efficiently run blast in multicore systems, as well as rough taxonomomic annoation using BASTA LCA
Home-page: https://github.com/jshleap/justblast
Author: jshleap
Author-email: jshleap@gmail.com
License: GNU v3
Platform: UNKNOWN
Requires-Python: >=3.6
Requires-Dist: matplotlib (==3.3.2)
Requires-Dist: numpy (==1.19.1)
Requires-Dist: termcolor (==1.1.0)
Requires-Dist: dask (==2.22.0)
Requires-Dist: pyfaidx (==0.5.9.1)
Requires-Dist: dill (==0.3.2)
Requires-Dist: psutil (==5.7.2)
Requires-Dist: pandas (==1.0.5)
Requires-Dist: tqdm (==4.49.0)
Requires-Dist: joblib (==0.16.0)
Requires-Dist: dask-mpi (==2.21.0)
